

[
    {
        "Destinos": [
            {
                "Nombre": "Marcela",
                "Edad": 55,
                "Servicio": "excelente",
                "Descripcion": "Lugar c贸modo, divertido, muchas cosas para hacer",
                "Origen": "Chile",
                "image": "https://apolagarrone.github.io/TP2024_1C_Equipo20_CaC/img/personas/luciaa.jpg"
            },
            {
                "Nombre": "Juan",
                "Edad": 55,
                "Servicio": "excelente",
                "Descripcion": "Lugar c贸modo, divertido, muchas cosas para hacer",
                "Origen": "Chile",
                "image": "https://apolagarrone.github.io/TP2024_1C_Equipo20_CaC/img/personas/juan.jpg"
            },
            {
                "Nombre": "Martina",
                "Edad": 55,
                "Servicio": "excelente",
                "Descripcion": "Lugar c贸modo, divertido, muchas cosas para hacer",
                "Origen": "Chile",
                "image": "https://apolagarrone.github.io/TP2024_1C_Equipo20_CaC/img/personas/marcelaa.jpg"
            },
            {
                "Nombre": "Pablo",
                "Edad": 55,
                "Servicio": "excelente",
                "Descripcion": "Lugar c贸modo, divertido, muchas cosas para hacer",
                "Origen": "Chile",
                "image": "https://apolagarrone.github.io/TP2024_1C_Equipo20_CaC/img/personas/pablo.jpg"
            }
        ]
    }
]




	
